{"g10537.t":{"prefix":["g10537.t1"],"exact":[]},"g4526":{"prefix":["g4526.t1"],"exact":[]},"g9276.t1":{"prefix":[],"exact":[["g9276.t1",0,"g9276.t1","scaffold167size278505",165609,170280]]},"g5363.":{"prefix":["g5363.t1"],"exact":[]},"g8287.t1":{"prefix":[],"exact":[["g8287.t1",0,"g8287.t1","scaffold138size195197",151505,161014]]},"scaffold432si":{"exact":[],"prefix":["scaffold432size715"]},"g7138.t1":{"prefix":[],"exact":[["g7138.t1",0,"g7138.t1","scaffold106size130129",64454,66420]]},"g10712.t":{"prefix":["g10712.t1","g10712.t2"],"exact":[]},"g1182.":{"exact":[],"prefix":["g1182.t1"]},"g1394.t":{"prefix":["g1394.t1"],"exact":[]},"g3386.t":{"prefix":["g3386.t1"],"exact":[]},"g269":{"exact":[],"prefix":["g2690.t1","g2691.t1","g2692.t1","g2693.t1","g2694.t1","g2695.t1","g2696.t1","g2697.t1","g2698.t1","g2699.t1","g269.t1"]},"g3215.t1":{"prefix":[],"exact":[["g3215.t1",0,"g3215.t1","scaffold42size402326",123878,133890]]},"g8471.t":{"prefix":["g8471.t1"],"exact":[]},"g418.":{"prefix":["g418.t1"],"exact":[]},"scaffold285size16064":{"prefix":[],"exact":[["scaffold285size16064",null,"scaffold285size16064",null,0,15864,20000]]},"g4346.t":{"exact":[],"prefix":["g4346.t1"]},"g6784.t1":{"exact":[["g6784.t1",0,"g6784.t1","scaffold99size162308",38985,45546]],"prefix":[]},"g7083":{"prefix":["g7083.t1"],"exact":[]},"g2796.t":{"exact":[],"prefix":["g2796.t1"]},"g5573.t":{"prefix":["g5573.t1"],"exact":[]},"g2126":{"prefix":["g2126.t1"],"exact":[]},"g7600":{"prefix":["g7600.t1"],"exact":[]},"g4377.t1":{"exact":[["g4377.t1",0,"g4377.t1","scaffold56size625172",543844,546999]],"prefix":[]},"g7079.t1":{"exact":[["g7079.t1",0,"g7079.t1","scaffold105size381750",200133,202667]],"prefix":[]},"g8151":{"exact":[],"prefix":["g8151.t1"]},"g7720.t":{"exact":[],"prefix":["g7720.t1"]},"g4322.t":{"exact":[],"prefix":["g4322.t1"]},"g258.":{"exact":[],"prefix":["g258.t1"]},"g10139.t1":{"exact":[["g10139.t1",0,"g10139.t1","scaffold203size162201",85715,90840]],"prefix":[]},"g8854":{"prefix":["g8854.t1"],"exact":[]},"scaffold139siz":{"prefix":["scaffold139size324579"],"exact":[]},"g9220.t":{"exact":[],"prefix":["g9220.t1"]},"g8375.":{"exact":[],"prefix":["g8375.t1"]},"g4163.t":{"exact":[],"prefix":["g4163.t1"]},"g2967.t":{"exact":[],"prefix":["g2967.t1"]},"g9863.":{"exact":[],"prefix":["g9863.t1"]},"g198":{"prefix":["g1980.t1","g1981.t1","g1982.t1","g1983.t1","g1984.t1","g1985.t1","g1986.t1","g1987.t1","g1988.t1","g1989.t1","g1989.t2","g198.t1"],"exact":[]},"g10635.t1":{"prefix":[],"exact":[["g10635.t1",0,"g10635.t1","scaffold241size37723",25375,34038]]},"g10966":{"prefix":["g10966.t1"],"exact":[]},"scaffold8siz":{"exact":[],"prefix":["scaffold8size161185"]},"g10078.t1":{"prefix":[],"exact":[["g10078.t1",0,"g10078.t1","scaffold200size30219",14525,17730]]},"g2523.t1":{"prefix":[],"exact":[["g2523.t1",0,"g2523.t1","scaffold35size955323",529568,531484]]},"g1200":{"exact":[],"prefix":["g1200.t1"]},"scaffold456si":{"exact":[],"prefix":["scaffold456size1368"]},"g1888.":{"prefix":["g1888.t1"],"exact":[]},"g7925.t1":{"prefix":[],"exact":[["g7925.t1",0,"g7925.t1","scaffold128size59112",2515,7216]]},"g10574.":{"prefix":["g10574.t1"],"exact":[]},"g187.t":{"prefix":["g187.t1"],"exact":[]},"g9061.t":{"exact":[],"prefix":["g9061.t1"]},"g1556.":{"prefix":["g1556.t1"],"exact":[]},"g1179.t":{"exact":[],"prefix":["g1179.t1"]},"g5386.t1":{"exact":[["g5386.t1",0,"g5386.t1","scaffold68size769518",575734,577881]],"prefix":[]},"g2090.":{"exact":[],"prefix":["g2090.t1"]},"g7967.":{"exact":[],"prefix":["g7967.t1"]},"g3354.t1":{"exact":[["g3354.t1",0,"g3354.t1","scaffold43size560705",456766,459971]],"prefix":[]},"g9677.":{"prefix":["g9677.t1"],"exact":[]},"g3458.t1":{"exact":[["g3458.t1",0,"g3458.t1","scaffold46size399386",49236,51730]],"prefix":[]},"g1483":{"exact":[],"prefix":["g1483.t1"]},"g21.":{"exact":[],"prefix":["g21.t1"]},"g9232":{"prefix":["g9232.t1"],"exact":[]},"g8535.":{"exact":[],"prefix":["g8535.t1"]},"g562.t1":{"prefix":[],"exact":[["g562.t1",0,"g562.t1","scaffold11size674165",533824,536199]]},"g8423":{"exact":[],"prefix":["g8423.t1"]},"g7505.t":{"exact":[],"prefix":["g7505.t1"]},"g8415.t":{"prefix":["g8415.t1"],"exact":[]},"g2903.t":{"exact":[],"prefix":["g2903.t1"]},"g9244.t":{"exact":[],"prefix":["g9244.t1"]},"g4107.t":{"exact":[],"prefix":["g4107.t1"]},"g4875.":{"exact":[],"prefix":["g4875.t1"]},"g3146.":{"prefix":["g3146.t1"],"exact":[]},"g7775.t1":{"prefix":[],"exact":[["g7775.t1",0,"g7775.t1","scaffold124size214254",136615,145670]]},"g7744.t":{"exact":[],"prefix":["g7744.t1"]},"g10774.t1":{"prefix":[],"exact":[["g10774.t1",0,"g10774.t1","scaffold256size27518",9696,11390]]},"g6271.":{"exact":[],"prefix":["g6271.t1"]},"g9169.":{"prefix":["g9169.t1"],"exact":[]},"g9740":{"exact":[],"prefix":["g9740.t1"]},"scaffold466size":{"prefix":["scaffold466size429"],"exact":[]},"g6088.t1":{"prefix":[],"exact":[["g6088.t1",0,"g6088.t1","scaffold83size925501",355123,357318]]},"g6043.t1":{"prefix":[],"exact":[["g6043.t1",0,"g6043.t1","scaffold83size925501",146936,150290]]},"g10334.":{"exact":[],"prefix":["g10334.t1"]},"g4236.t1":{"exact":[["g4236.t1",0,"g4236.t1","scaffold55size253303",104815,108180]],"prefix":[]},"g9729.":{"exact":[],"prefix":["g9729.t1"]},"scaffold312size46":{"exact":[],"prefix":["scaffold312size4675"]},"g4208":{"exact":[],"prefix":["g4208.t1"]},"g10511":{"prefix":["g10511.t1"],"exact":[]},"scaffold224size240":{"exact":[],"prefix":["scaffold224size24073"]},"g10865.t1":{"prefix":[],"exact":[["g10865.t1",0,"g10865.t1","scaffold271size38761",19436,21510]]},"g5337":{"prefix":["g5337.t1"],"exact":[]},"g306.":{"prefix":["g306.t1"],"exact":[]},"scaffold86s":{"exact":[],"prefix":["scaffold86size188271"]},"scaffold272size42720":{"exact":[["scaffold272size42720",null,"scaffold272size42720",null,0,42220,20000]],"prefix":[]},"g2823":{"prefix":["g2823.t1"],"exact":[]},"g10924.t1":{"exact":[["g10924.t1",0,"g10924.t1","scaffold281size29747",26405,28577]],"prefix":[]},"g7864.t1":{"exact":[["g7864.t1",0,"g7864.t1","scaffold126size432883",237602,245286]],"prefix":[]},"g3737":{"prefix":["g3737.t1"],"exact":[]},"g9337.t1":{"prefix":[],"exact":[["g9337.t1",0,"g9337.t1","scaffold169size252111",206007,215311]]},"g10063":{"exact":[],"prefix":["g10063.t1"]},"g7839.":{"exact":[],"prefix":["g7839.t1"]},"g6330.t":{"exact":[],"prefix":["g6330.t1"]},"g3519.t1":{"exact":[["g3519.t1",0,"g3519.t1","scaffold46size399386",370863,373487]],"prefix":[]},"g547":{"exact":[],"prefix":["g547.t1","g5470.t1","g5471.t1","g5472.t1","g5473.t1","g5474.t1","g5475.t1","g5476.t1","g5477.t1","g5478.t1","g5479.t1"]},"g8809.t":{"exact":[],"prefix":["g8809.t1"]},"g5523.":{"exact":[],"prefix":["g5523.t1"]},"g192.":{"exact":[],"prefix":["g192.t1"]},"g1408.":{"prefix":["g1408.t1"],"exact":[]},"g3706.":{"prefix":["g3706.t1"],"exact":[]},"g1060.t1":{"exact":[["g1060.t1",0,"g1060.t1","scaffold18size500504",18530,32270]],"prefix":[]},"g1959":{"prefix":["g1959.t1"],"exact":[]},"g2462.t1":{"prefix":[],"exact":[["g2462.t1",0,"g2462.t1","scaffold35size955323",182744,202308]]},"g3019":{"prefix":["g3019.t1"],"exact":[]},"g3592.":{"exact":[],"prefix":["g3592.t1"]},"g1248.":{"exact":[],"prefix":["g1248.t1"]},"g7561.t":{"prefix":["g7561.t1"],"exact":[]},"g6431.":{"prefix":["g6431.t1"],"exact":[]},"g4951":{"exact":[],"prefix":["g4951.t1"]},"g8540.t1":{"exact":[["g8540.t1",0,"g8540.t1","scaffold144size322648",120955,122810]],"prefix":[]},"g6011":{"prefix":["g6011.t1"],"exact":[]},"g4661.":{"prefix":["g4661.t1"],"exact":[]},"g10776.t":{"prefix":["g10776.t1"],"exact":[]},"g5732.t":{"prefix":["g5732.t1"],"exact":[]},"g6171.t":{"prefix":["g6171.t1"],"exact":[]},"g3018.":{"exact":[],"prefix":["g3018.t1"]},"g898.":{"prefix":["g898.t1"],"exact":[]},"g9005.t":{"prefix":["g9005.t1"],"exact":[]},"g5500.t1":{"exact":[["g5500.t1",0,"g5500.t1","scaffold70size243649",131226,133060]],"prefix":[]},"g10987.t":{"exact":[],"prefix":["g10987.t1"]},"g6354.t":{"prefix":["g6354.t1"],"exact":[]},"g11042.t1":{"prefix":[],"exact":[["g11042.t1",0,"g11042.t1","scaffold452size16250",7726,8430]]},"g8630.t":{"prefix":["g8630.t1"],"exact":[]},"g2608":{"prefix":["g2608.t1"],"exact":[]},"g10392":{"exact":[],"prefix":["g10392.t1"]},"g86.t":{"prefix":["g86.t1"],"exact":[]},"g3912.":{"exact":[],"prefix":["g3912.t1"]},"scaffold317size422":{"prefix":["scaffold317size4227"],"exact":[]},"g5517.t":{"prefix":["g5517.t1"],"exact":[]},"g5419":{"exact":[],"prefix":["g5419.t1"]},"g6914":{"exact":[],"prefix":["g6914.t1"]},"scaffold403size1028":{"exact":[["scaffold403size1028",null,"scaffold403size1028",null,0,1014,20000]],"prefix":[]},"g4054":{"prefix":["g4054.t1"],"exact":[]},"g1316.":{"exact":[],"prefix":["g1316.t1"]},"g7986":{"exact":[],"prefix":["g7986.t1"]},"g1338.t":{"exact":[],"prefix":["g1338.t1"]},"g1121.t1":{"prefix":[],"exact":[["g1121.t1",0,"g1121.t1","scaffold18size500504",385024,389488]]},"g7133.":{"prefix":["g7133.t1"],"exact":[]},"scaffold147size16":{"exact":[],"prefix":["scaffold147size169362"]},"scaffold246size8":{"exact":[],"prefix":["scaffold246size82704"]},"g6102.t1":{"prefix":[],"exact":[["g6102.t1",0,"g6102.t1","scaffold83size925501",421074,422418]]},"g4021.":{"prefix":["g4021.t1"],"exact":[]},"g1772":{"exact":[],"prefix":["g1772.t1"]},"g2444.":{"prefix":["g2444.t1"],"exact":[]},"g6115.t":{"exact":[],"prefix":["g6115.t1"]},"g7634.t1":{"prefix":[],"exact":[["g7634.t1",0,"g7634.t1","scaffold120size505066",228647,231112]]},"g5756.t":{"exact":[],"prefix":["g5756.t1"]},"g930":{"prefix":["g9300.t1","g9301.t1","g9302.t1","g9303.t1","g9304.t1","g9305.t1","g9306.t1","g9307.t1","g9308.t1","g9309.t1","g930.t1"],"exact":[]},"g8401.t1":{"exact":[["g8401.t1",0,"g8401.t1","scaffold140size340415",235042,239268]],"prefix":[]},"g2454":{"exact":[],"prefix":["g2454.t1"]},"g8654.t":{"prefix":["g8654.t1","g8654.t2"],"exact":[]},"g6563":{"exact":[],"prefix":["g6563.t1"]},"g3658.":{"prefix":["g3658.t1"],"exact":[]},"g2204.":{"exact":[],"prefix":["g2204.t1"]},"g5645":{"prefix":["g5645.t1"],"exact":[]},"g6895.t1":{"exact":[["g6895.t1",0,"g6895.t1","scaffold102size408046",20055,30130]],"prefix":[]},"g6692":{"prefix":["g6692.t1"],"exact":[]},"g423.t1":{"prefix":[],"exact":[["g423.t1",0,"g423.t1","scaffold10size344057",69045,72162]]},"g7773.":{"prefix":["g7773.t1"],"exact":[]},"g10553.t":{"prefix":["g10553.t1"],"exact":[]},"g7372":{"prefix":["g7372.t1"],"exact":[]},"g3493.t1":{"prefix":[],"exact":[["g3493.t1",0,"g3493.t1","scaffold46size399386",210236,213087]]},"g3245":{"prefix":["g3245.t1"],"exact":[]},"scaffold483size":{"prefix":["scaffold483size330"],"exact":[]},"g5441.t1":{"prefix":[],"exact":[["g5441.t1",0,"g5441.t1","scaffold69size333042",155276,164685]]},"g546.":{"prefix":["g546.t1"],"exact":[]},"g7919.t":{"prefix":["g7919.t1"],"exact":[]},"scaffold151s":{"exact":[],"prefix":["scaffold151size116517"]},"g9037.":{"prefix":["g9037.t1"],"exact":[]}}