{"scaffold79size34947":{"exact":[],"prefix":["scaffold79size349471"]},"g5527":{"exact":[],"prefix":["g5527.t1"]},"g1722.t1":{"prefix":[],"exact":[["g1722.t1",0,"g1722.t1","scaffold24size454154",422921,424934]]},"g3557.t1":{"exact":[["g3557.t1",0,"g3557.t1","scaffold48size475208",2095,5400]],"prefix":[]},"g479":{"prefix":["g479.t1","g4790.t1","g4791.t1","g4792.t1","g4793.t1","g4794.t1","g4795.t1","g4796.t1","g4797.t1","g4798.t1","g4799.t1"],"exact":[]},"g2265.":{"exact":[],"prefix":["g2265.t1"]},"scaffold79":{"exact":[],"prefix":["scaffold79size349471"]},"g5542.":{"prefix":["g5542.t1"],"exact":[]},"g6701.t1":{"prefix":[],"exact":[["g6701.t1",0,"g6701.t1","scaffold96size800595",756695,760175]]},"g5950":{"prefix":["g5950.t1"],"exact":[]},"g527.":{"exact":[],"prefix":["g527.t1"]},"g4583.t":{"prefix":["g4583.t1"],"exact":[]},"g5193.t":{"exact":[],"prefix":["g5193.t1"]},"g9608.t":{"exact":[],"prefix":["g9608.t1"]},"g9482.":{"exact":[],"prefix":["g9482.t1"]},"g3543.t":{"prefix":["g3543.t1"],"exact":[]},"g1551.t":{"prefix":["g1551.t1"],"exact":[]},"g7858.":{"exact":[],"prefix":["g7858.t1"]},"g367.":{"prefix":["g367.t1"],"exact":[]},"g3290.t1":{"exact":[["g3290.t1",0,"g3290.t1","scaffold43size560705",157077,165940]],"prefix":[]},"scaffold9s":{"prefix":["scaffold9size255328"],"exact":[]},"g6187.t1":{"prefix":[],"exact":[["g6187.t1",0,"g6187.t1","scaffold83size925501",758605,760760]]},"g2425.":{"prefix":["g2425.t1"],"exact":[]},"g4814.":{"prefix":["g4814.t1"],"exact":[]},"g4494.":{"exact":[],"prefix":["g4494.t1"]},"g7152.":{"exact":[],"prefix":["g7152.t1"]},"scaffold83siz":{"exact":[],"prefix":["scaffold83size925501"]},"g7308.t":{"prefix":["g7308.t1"],"exact":[]},"g503.t":{"exact":[],"prefix":["g503.t1"]},"g8091.t":{"exact":[],"prefix":["g8091.t1"]},"g8654.t2":{"prefix":[],"exact":[["g8654.t2",0,"g8654.t2","scaffold147size169362",20815,23144]]},"g1867":{"prefix":["g1867.t1"],"exact":[]},"scaffold177siz":{"prefix":["scaffold177size107572"],"exact":[]},"g479.":{"exact":[],"prefix":["g479.t1"]},"scaffold446size96":{"exact":[],"prefix":["scaffold446size9672"]},"scaffold130s":{"exact":[],"prefix":["scaffold130size344546"]},"g5585.t1":{"exact":[["g5585.t1",0,"g5585.t1","scaffold73size81698",68225,69420]],"prefix":[]},"g7298.":{"exact":[],"prefix":["g7298.t1"]},"g9616.":{"prefix":["g9616.t1"],"exact":[]},"g1663.t1":{"exact":[["g1663.t1",0,"g1663.t1","scaffold24size454154",130476,138110]],"prefix":[]},"g7010":{"exact":[],"prefix":["g7010.t1"]},"g4435.t1":{"exact":[["g4435.t1",0,"g4435.t1","scaffold58size836374",197287,202791]],"prefix":[]},"g10858":{"exact":[],"prefix":["g10858.t1"]},"scaffold137size217426":{"prefix":[],"exact":[["scaffold137size217426",null,"scaffold137size217426",null,0,214799,20000]]},"g3127":{"prefix":["g3127.t1"],"exact":[]},"g10355.":{"prefix":["g10355.t1"],"exact":[]},"g9481.t":{"prefix":["g9481.t1"],"exact":[]},"g2376.t":{"prefix":["g2376.t1"],"exact":[]},"g1833.t1":{"prefix":[],"exact":[["g1833.t1",0,"g1833.t1","scaffold25size587538",503033,505871]]},"scaffold31size":{"exact":[],"prefix":["scaffold31size153507"]},"g10673":{"exact":[],"prefix":["g10673.t1"]},"g9855":{"exact":[],"prefix":["g9855.t1"]},"g10582":{"exact":[],"prefix":["g10582.t1"]},"g9748.":{"exact":[],"prefix":["g9748.t1"]},"scaffold157size1995":{"exact":[],"prefix":["scaffold157size199512"]},"g6082":{"prefix":["g6082.t1"],"exact":[]},"g4574.t1":{"exact":[["g4574.t1",0,"g4574.t1","scaffold58size836374",811914,819443]],"prefix":[]},"g9855.t":{"exact":[],"prefix":["g9855.t1"]},"g1599.t":{"exact":[],"prefix":["g1599.t1"]},"g3997.t":{"prefix":["g3997.t1"],"exact":[]},"g1774.t":{"exact":[],"prefix":["g1774.t1"]},"g1410":{"prefix":["g1410.t1"],"exact":[]},"g3639.":{"prefix":["g3639.t1"],"exact":[]},"g8314.":{"exact":[],"prefix":["g8314.t1"]},"g9238.t1":{"prefix":[],"exact":[["g9238.t1",0,"g9238.t1","scaffold166size161682",101690,103860]]},"g4339.t1":{"prefix":[],"exact":[["g4339.t1",0,"g4339.t1","scaffold56size625172",369674,372699]]},"g7586.":{"exact":[],"prefix":["g7586.t1"]},"g7037.t1":{"exact":[["g7037.t1",0,"g7037.t1","scaffold105size381750",6825,9494]],"prefix":[]},"g1985.t":{"prefix":["g1985.t1"],"exact":[]},"scaffold32si":{"exact":[],"prefix":["scaffold32size793360"]},"g357":{"prefix":["g3570.t1","g3571.t1","g3572.t1","g3573.t1","g3574.t1","g3574.t2","g3575.t1","g3576.t1","g3577.t1","g3578.t1","g3579.t1","g3579.t2","g357.t1"],"exact":[]},"g3766.t":{"prefix":["g3766.t1"],"exact":[]},"g9422":{"prefix":["g9422.t1"],"exact":[]},"g9056.":{"prefix":["g9056.t1"],"exact":[]},"scaffold48siz":{"prefix":["scaffold48size475208"],"exact":[]},"g2320.t1":{"prefix":[],"exact":[["g2320.t1",0,"g2320.t1","scaffold33size816250",554020,557739]]},"g1972.t1":{"exact":[["g1972.t1",0,"g1972.t1","scaffold28size85466",61335,65660]],"prefix":[]},"g742.t":{"prefix":["g742.t1"],"exact":[]},"g1469.":{"exact":[],"prefix":["g1469.t1"]},"scaffold56si":{"exact":[],"prefix":["scaffold56size625172"]},"g7176.t1":{"exact":[["g7176.t1",0,"g7176.t1","scaffold107size291776",121675,124130]],"prefix":[]},"g10781.":{"prefix":["g10781.t1"],"exact":[]},"g239.":{"prefix":["g239.t1"],"exact":[]},"g6945.t":{"exact":[],"prefix":["g6945.t1"]},"scaffold253size3582":{"exact":[],"prefix":["scaffold253size35821"]},"g3767.":{"exact":[],"prefix":["g3767.t1"]},"g3527.t":{"exact":[],"prefix":["g3527.t1"]},"g3702.t":{"prefix":["g3702.t1"],"exact":[]},"g8059.t":{"prefix":["g8059.t1"],"exact":[]},"g7149.t":{"prefix":["g7149.t1"],"exact":[]},"g8233":{"prefix":["g8233.t1"],"exact":[]},"g220.t1":{"prefix":[],"exact":[["g220.t1",0,"g220.t1","scaffold5size201749",154276,159740]]},"g1929.t":{"exact":[],"prefix":["g1929.t1"]},"g1229.":{"exact":[],"prefix":["g1229.t1"]},"g726.t":{"prefix":["g726.t1","g726.t2"],"exact":[]},"g567.t":{"exact":[],"prefix":["g567.t1"]},"g6084.":{"prefix":["g6084.t1"],"exact":[]},"g788":{"prefix":["g7880.t1","g7881.t1","g7882.t1","g7883.t1","g7884.t1","g7885.t1","g7886.t2","g7886.t1","g7887.t1","g7888.t1","g7889.t1","g788.t1"],"exact":[]},"g1293":{"prefix":["g1293.t1"],"exact":[]},"scaffold266size45":{"prefix":["scaffold266size45880"],"exact":[]},"scaffold389size3027":{"exact":[["scaffold389size3027",null,"scaffold389size3027",null,0,2996,20000]],"prefix":[]},"g7181.t":{"exact":[],"prefix":["g7181.t1"]},"g2261.t1":{"exact":[["g2261.t1",0,"g2261.t1","scaffold33size816250",237938,242392]],"prefix":[]},"g6921.t":{"prefix":["g6921.t1"],"exact":[]},"g3609":{"exact":[],"prefix":["g3609.t1"]},"scaffold100size11373":{"prefix":["scaffold100size113733"],"exact":[]},"g3455":{"prefix":["g3455.t1"],"exact":[]},"g5209":{"prefix":["g5209.t1"],"exact":[]},"g65.t1":{"prefix":[],"exact":[["g65.t1",0,"g65.t1","scaffold2size250259",188307,190582]]},"g9802.":{"prefix":["g9802.t1"],"exact":[]},"g6601":{"exact":[],"prefix":["g6601.t1"]},"g4336":{"exact":[],"prefix":["g4336.t1"]},"g8741":{"exact":[],"prefix":["g8741.t1"]},"g8218.t":{"prefix":["g8218.t1"],"exact":[]},"g1710.t":{"exact":[],"prefix":["g1710.t1"]},"g7906.":{"exact":[],"prefix":["g7906.t1"]},"g2244":{"prefix":["g2244.t1"],"exact":[]},"g6450.":{"prefix":["g6450.t1"],"exact":[]},"g3127.":{"exact":[],"prefix":["g3127.t1"]},"g10036.t1":{"exact":[["g10036.t1",0,"g10036.t1","scaffold197size164785",160175,162430]],"prefix":[]},"g1377.":{"exact":[],"prefix":["g1377.t1"]},"scaffold343":{"exact":[],"prefix":["scaffold343size2445"]},"g9108.":{"prefix":["g9108.t1"],"exact":[]},"g625":{"prefix":["g625.t1","g6250.t1","g6251.t1","g6252.t1","g6253.t1","g6254.t1","g6255.t1","g6256.t1","g6257.t1","g6257.t2","g6257.t3","g6258.t1","g6259.t1"],"exact":[]},"g6591.t":{"prefix":["g6591.t1"],"exact":[]},"g7562":{"prefix":["g7562.t1"],"exact":[]},"g5289.t1":{"exact":[["g5289.t1",0,"g5289.t1","scaffold68size769518",104725,113406]],"prefix":[]},"g7693":{"prefix":["g7693.t1"],"exact":[]},"g3822":{"exact":[],"prefix":["g3822.t1"]},"g1535.t":{"exact":[],"prefix":["g1535.t1"]},"g6373":{"prefix":["g6373.t1"],"exact":[]},"g6210.":{"exact":[],"prefix":["g6210.t1"]},"g4040.":{"exact":[],"prefix":["g4040.t1"]},"scaffold293si":{"prefix":["scaffold293size8330"],"exact":[]},"g5302.":{"prefix":["g5302.t1"],"exact":[]},"g9449.t":{"prefix":["g9449.t1"],"exact":[]},"g10301":{"prefix":["g10301.t1"],"exact":[]},"g10995.":{"prefix":["g10995.t1"],"exact":[]},"g10177.t1":{"prefix":[],"exact":[["g10177.t1",0,"g10177.t1","scaffold205size75908",47255,49160]]},"g9475.t1":{"prefix":[],"exact":[["g9475.t1",0,"g9475.t1","scaffold175size187736",41616,45970]]},"g40.":{"prefix":["g40.t1"],"exact":[]},"g4933.t":{"prefix":["g4933.t1"],"exact":[]},"g2137.t":{"prefix":["g2137.t1"],"exact":[]},"g4600.":{"exact":[],"prefix":["g4600.t1"]},"g11017.":{"prefix":["g11017.t1"],"exact":[]},"g8180.":{"exact":[],"prefix":["g8180.t1"]},"g3416.t1":{"prefix":[],"exact":[["g3416.t1",0,"g3416.t1","scaffold44size245767",189749,198143]]},"g8202.t1":{"exact":[["g8202.t1",0,"g8202.t1","scaffold136size209014",103966,114570]],"prefix":[]},"g10396.t":{"exact":[],"prefix":["g10396.t1","g10396.t2","g10396.t3","g10396.t4"]},"g2736":{"exact":[],"prefix":["g2736.t1"]},"g4644":{"exact":[],"prefix":["g4644.t1"]},"g3079.":{"prefix":["g3079.t1"],"exact":[]},"g4418":{"prefix":["g4418.t1"],"exact":[]},"g6718.t":{"exact":[],"prefix":["g6718.t1"]},"g3973.":{"exact":[],"prefix":["g3973.t1"]},"g9534.t1":{"exact":[["g9534.t1",0,"g9534.t1","scaffold178size185641",19105,20730]],"prefix":[]},"scaffold304size":{"prefix":["scaffold304size5117"],"exact":[]},"g1162":{"prefix":["g1162.t1","g1162.t2"],"exact":[]},"g5242.t1":{"prefix":[],"exact":[["g5242.t1",0,"g5242.t1","scaffold67size576133",443884,446999]]},"g1537.":{"exact":[],"prefix":["g1537.t1"]},"g7915":{"prefix":["g7915.t1"],"exact":[]},"g6640.t1":{"exact":[["g6640.t1",0,"g6640.t1","scaffold96size800595",467296,468730]],"prefix":[]},"g4278.t1":{"exact":[["g4278.t1",0,"g4278.t1","scaffold56size625172",59266,61300]],"prefix":[]},"g6559.t":{"exact":[],"prefix":["g6559.t1"]},"g2018":{"exact":[],"prefix":["g2018.t1"]},"g9379.t1":{"prefix":[],"exact":[["g9379.t1",0,"g9379.t1","scaffold171size302023",89305,90504]]},"scaffold161size4504":{"exact":[],"prefix":["scaffold161size45044"]},"g9150":{"prefix":["g9150.t1"],"exact":[]},"g9831.t":{"prefix":["g9831.t1"],"exact":[]},"g5055":{"prefix":["g5055.t1"],"exact":[]},"g361.t1":{"prefix":[],"exact":[["g361.t1",0,"g361.t1","scaffold9size255328",33163,36610]]},"g5303.t1":{"exact":[["g5303.t1",0,"g5303.t1","scaffold68size769518",180461,183105]],"prefix":[]},"scaffold156size1":{"exact":[],"prefix":["scaffold156size149216"]},"g2312.t":{"prefix":["g2312.t1"],"exact":[]},"g7712.":{"exact":[],"prefix":["g7712.t1"]},"g6810.t1":{"prefix":[],"exact":[["g6810.t1",0,"g6810.t1","scaffold100size113733",15690,17670]]},"g5688.":{"exact":[],"prefix":["g5688.t1"]},"g5196.":{"prefix":["g5196.t1"],"exact":[]},"g10515.":{"prefix":["g10515.t1"],"exact":[]},"g8554.":{"exact":[],"prefix":["g8554.t1"]},"g8388.t1":{"exact":[["g8388.t1",0,"g8388.t1","scaffold140size340415",178795,182962]],"prefix":[]},"g6951.t1":{"exact":[["g6951.t1",0,"g6951.t1","scaffold102size408046",310666,319160]],"prefix":[]},"g8343.t1":{"exact":[["g8343.t1",0,"g8343.t1","scaffold139size324579",261675,263710]],"prefix":[]},"g4957.t":{"exact":[],"prefix":["g4957.t1"]},"g8484.t1":{"prefix":[],"exact":[["g8484.t1",0,"g8484.t1","scaffold143size412725",261819,264434]]},"g2153.t":{"exact":[],"prefix":["g2153.t1"]},"g6987":{"exact":[],"prefix":["g6987.t1"]}}