{"g10989.":{"exact":[],"prefix":["g10989.t1"]},"g7284.t":{"exact":[],"prefix":["g7284.t1"]},"g6992.":{"exact":[],"prefix":["g6992.t1"]},"g7729.t1":{"exact":[["g7729.t1",0,"g7729.t1","scaffold123size117197",37275,38830]],"prefix":[]},"g465.":{"exact":[],"prefix":["g465.t1"]},"g2384":{"prefix":["g2384.t1"],"exact":[]},"g77.t1":{"exact":[["g77.t1",0,"g77.t1","scaffold3size261092",686,5000]],"prefix":[]},"g4629":{"exact":[],"prefix":["g4629.t1"]},"g9569.t":{"prefix":["g9569.t1"],"exact":[]},"g8308.":{"exact":[],"prefix":["g8308.t1"]},"g5694.":{"exact":[],"prefix":["g5694.t1"]},"g4396.":{"prefix":["g4396.t1"],"exact":[]},"g2332.t1":{"exact":[["g2332.t1",0,"g2332.t1","scaffold33size816250",591775,594289]],"prefix":[]},"g6988.t1":{"prefix":[],"exact":[["g6988.t1",0,"g6988.t1","scaffold103size229685",93816,99790]]},"g6943.t1":{"exact":[["g6943.t1",0,"g6943.t1","scaffold102size408046",258545,260370]],"prefix":[]},"g8351.t1":{"exact":[["g8351.t1",0,"g8351.t1","scaffold139size324579",297425,300680]],"prefix":[]},"g1621":{"prefix":["g1621.t1"],"exact":[]},"g10442":{"exact":[],"prefix":["g10442.t1"]},"g9975.t":{"exact":[],"prefix":["g9975.t1"]},"g8496.t1":{"exact":[["g8496.t1",0,"g8496.t1","scaffold143size412725",320358,322444]],"prefix":[]},"g9728.t":{"exact":[],"prefix":["g9728.t1"]},"g6699.t1":{"exact":[["g6699.t1",0,"g6699.t1","scaffold96size800595",750669,751845]],"prefix":[]},"g8681":{"exact":[],"prefix":["g8681.t1"]},"scaffold14":{"exact":[],"prefix":["scaffold140size340415","scaffold141size62350","scaffold142size44553","scaffold143size412725","scaffold144size322648","scaffold145size154460","scaffold146size198039","scaffold147size169362","scaffold148size197089","scaffold149size273598","scaffold14size392756"]},"g9754.":{"prefix":["g9754.t1"],"exact":[]},"g10130":{"prefix":["g10130.t1"],"exact":[]},"g3595":{"exact":[],"prefix":["g3595.t1"]},"g3438":{"prefix":["g3438.t1"],"exact":[]},"g10093.t":{"prefix":["g10093.t1","g10093.t2"],"exact":[]},"g4802":{"exact":[],"prefix":["g4802.t1"]},"g2439.":{"exact":[],"prefix":["g2439.t1"]},"g7221":{"prefix":["g7221.t1"],"exact":[]},"g10728.t1":{"exact":[["g10728.t1",0,"g10728.t1","scaffold251size33997",7205,21070]],"prefix":[]},"g8394.t":{"prefix":["g8394.t1"],"exact":[]},"g9940.":{"exact":[],"prefix":["g9940.t1","g9940.t2"]},"g1471.t":{"prefix":["g1471.t1"],"exact":[]},"g606.t":{"prefix":["g606.t1"],"exact":[]},"g9784.t":{"prefix":["g9784.t1"],"exact":[]},"g3065.":{"prefix":["g3065.t1"],"exact":[]},"g9467.t1":{"prefix":[],"exact":[["g9467.t1",0,"g9467.t1","scaffold174size79108",62866,64360]]},"g5311.t1":{"exact":[["g5311.t1",0,"g5311.t1","scaffold68size769518",222180,225695]],"prefix":[]},"g7838.t1":{"prefix":[],"exact":[["g7838.t1",0,"g7838.t1","scaffold126size432883",121066,124820]]},"g7228.t":{"exact":[],"prefix":["g7228.t1"]},"g5296.t":{"exact":[],"prefix":["g5296.t1"]},"scaffold91siz":{"exact":[],"prefix":["scaffold91size74715"]},"g2017.t":{"exact":[],"prefix":["g2017.t1"]},"g2327.":{"exact":[],"prefix":["g2327.t1"]},"g5038":{"prefix":["g5038.t1"],"exact":[]},"g5880.":{"exact":[],"prefix":["g5880.t1"]},"g3664":{"prefix":["g3664.t1"],"exact":[]},"g1235.":{"prefix":["g1235.t1"],"exact":[]},"g8682.":{"prefix":["g8682.t1"],"exact":[]},"g6801.t":{"exact":[],"prefix":["g6801.t1"]},"g2229":{"exact":[],"prefix":["g2229.t1"]},"g4102.":{"prefix":["g4102.t1"],"exact":[]},"g1671.t1":{"exact":[["g1671.t1",0,"g1671.t1","scaffold24size454154",178860,180420]],"prefix":[]},"g10217.":{"exact":[],"prefix":["g10217.t1"]},"g7668.t1":{"prefix":[],"exact":[["g7668.t1",0,"g7668.t1","scaffold120size505066",417511,418386]]},"g10083.":{"exact":[],"prefix":["g10083.t1"]},"g225.":{"exact":[],"prefix":["g225.t1"]},"g7025.t1":{"exact":[["g7025.t1",0,"g7025.t1","scaffold104size98775",34616,37170]],"prefix":[]},"g2970":{"exact":[],"prefix":["g2970.t1"]},"g423.t":{"exact":[],"prefix":["g423.t1"]},"g10839.t1":{"exact":[["g10839.t1",0,"g10839.t1","scaffold267size27658",25465,27336]],"prefix":[]},"g9361":{"exact":[],"prefix":["g9361.t1"]},"g7844.":{"prefix":["g7844.t1"],"exact":[]},"g5080.t2":{"prefix":[],"exact":[["g5080.t2",0,"g5080.t2","scaffold64size547194",453542,459936]]},"g9911.t":{"exact":[],"prefix":["g9911.t1"]},"g9090":{"prefix":["g9090.t1"],"exact":[]},"g8256.":{"exact":[],"prefix":["g8256.t1"]},"g5195":{"prefix":["g5195.t1","g5195.t2"],"exact":[]},"g4784":{"prefix":["g4784.t1"],"exact":[]},"g6142":{"exact":[],"prefix":["g6142.t1"]},"g662.t":{"exact":[],"prefix":["g662.t1"]},"g3625.":{"exact":[],"prefix":["g3625.t1"]},"g5264":{"prefix":["g5264.t1"],"exact":[]},"scaffold7size272":{"prefix":["scaffold7size272406"],"exact":[]},"g648":{"prefix":["g648.t1","g6480.t1","g6481.t1","g6482.t1","g6483.t1","g6484.t1","g6485.t1","g6486.t1","g6487.t1","g6488.t1","g6489.t1"],"exact":[]},"g1730.t1":{"exact":[["g1730.t1",0,"g1730.t1","scaffold25size587538",4335,18632]],"prefix":[]},"g6512.":{"exact":[],"prefix":["g6512.t1"]},"scaffold6size1":{"prefix":["scaffold6size114993"],"exact":[]},"g4686.t":{"exact":[],"prefix":["g4686.t1"]},"g3831.":{"exact":[],"prefix":["g3831.t1"]},"g3316":{"prefix":["g3316.t1"],"exact":[]},"g9380.":{"exact":[],"prefix":["g9380.t1"]},"scaffold18size5005":{"exact":[],"prefix":["scaffold18size500504"]},"g8816.t2":{"prefix":[],"exact":[["g8816.t2",0,"g8816.t2","scaffold152size126932",15886,20580]]},"g7979.t1":{"exact":[["g7979.t1",0,"g7979.t1","scaffold129size234716",227164,229261]],"prefix":[]},"g232.t1":{"exact":[["g232.t1",0,"g232.t1","scaffold6size114993",25865,31670]],"prefix":[]},"g4427.t1":{"exact":[["g4427.t1",0,"g4427.t1","scaffold58size836374",138717,150560]],"prefix":[]},"g5716":{"prefix":["g5716.t1"],"exact":[]},"g10835":{"exact":[],"prefix":["g10835.t1"]},"g8179.t":{"exact":[],"prefix":["g8179.t1"]},"g3622.t":{"exact":[],"prefix":["g3622.t1"]},"g3545.t1":{"prefix":[],"exact":[["g3545.t1",0,"g3545.t1","scaffold47size158150",106200,107450]]},"g8896.":{"prefix":["g8896.t1"],"exact":[]},"g6694.t":{"exact":[],"prefix":["g6694.t1"]},"scaffold165siz":{"exact":[],"prefix":["scaffold165size72941"]},"g1415.t":{"prefix":["g1415.t1"],"exact":[]},"g8416.":{"exact":[],"prefix":["g8416.t1"]},"g6098.":{"exact":[],"prefix":["g6098.t1"]},"g8907":{"prefix":["g8907.t1"],"exact":[]},"scaffold413size":{"exact":[],"prefix":["scaffold413size863"]},"g4808.":{"prefix":["g4808.t1"],"exact":[]},"g4813.t":{"exact":[],"prefix":["g4813.t1"]},"g3646.t":{"exact":[],"prefix":["g3646.t1"]},"g10024.t1":{"exact":[["g10024.t1",0,"g10024.t1","scaffold197size164785",82715,91770]],"prefix":[]},"g6430":{"prefix":["g6430.t1"],"exact":[]},"g414":{"exact":[],"prefix":["g414.t1","g4140.t1","g4141.t1","g4142.t1","g4143.t1","g4144.t1","g4145.t1","g4146.t1","g4147.t1","g4148.t1","g4149.t1"]},"scaffold196si":{"exact":[],"prefix":["scaffold196size57345"]},"g863":{"exact":[],"prefix":["g8630.t1","g8631.t1","g8632.t1","g8633.t1","g8634.t1","g8635.t1","g8636.t1","g8637.t1","g8638.t1","g8639.t1","g863.t1"]},"g9170.t2":{"prefix":[],"exact":[["g9170.t2",0,"g9170.t2","scaffold163size128485",45955,48840]]},"scaffold400":{"prefix":["scaffold400size1065"],"exact":[]},"g1475.":{"exact":[],"prefix":["g1475.t1"]},"g166":{"prefix":["g1660.t1","g1661.t1","g1662.t1","g1663.t1","g1663.t2","g1664.t1","g1665.t1","g1666.t1","g1667.t1","g1668.t1","g1669.t1","g166.t1"],"exact":[]},"g297":{"prefix":["g2970.t1","g2971.t1","g2972.t1","g2973.t1","g2974.t1","g2975.t1","g2976.t1","g2977.t1","g2978.t1","g2979.t1","g297.t1"],"exact":[]},"g7978":{"exact":[],"prefix":["g7978.t1"]},"g373.t1":{"prefix":[],"exact":[["g373.t1",0,"g373.t1","scaffold9size255328",84995,86420]]},"g3282.t1":{"prefix":[],"exact":[["g3282.t1",0,"g3282.t1","scaffold43size560705",126395,129025]]},"g447.t":{"prefix":["g447.t1"],"exact":[]},"g4475":{"exact":[],"prefix":["g4475.t1"]},"g7753":{"exact":[],"prefix":["g7753.t1"]},"g2567.":{"exact":[],"prefix":["g2567.t1"]},"g10998":{"prefix":["g10998.t1"],"exact":[]},"g4566.t1":{"prefix":[],"exact":[["g4566.t1",0,"g4566.t1","scaffold58size836374",780840,785219]]},"g2232.t":{"prefix":["g2232.t1"],"exact":[]},"g7164.t1":{"exact":[["g7164.t1",0,"g7164.t1","scaffold107size291776",68096,70800]],"prefix":[]},"g4877.t":{"prefix":["g4877.t1"],"exact":[]},"g3404.t1":{"exact":[["g3404.t1",0,"g3404.t1","scaffold44size245767",148173,151020]],"prefix":[]},"g3308.t1":{"exact":[["g3308.t1",0,"g3308.t1","scaffold43size560705",247180,249555]],"prefix":[]},"g3463.t":{"exact":[],"prefix":["g3463.t1"]},"g1353":{"prefix":["g1353.t1"],"exact":[]},"g7650.":{"prefix":["g7650.t1"],"exact":[]},"g6638.t":{"prefix":["g6638.t1"],"exact":[]},"scaffold221size138":{"exact":[],"prefix":["scaffold221size138246"]},"g2075":{"prefix":["g2075.t1","g2075.t2"],"exact":[]},"g10457.":{"exact":[],"prefix":["g10457.t1"]},"g6865.t":{"prefix":["g6865.t1"],"exact":[]},"g6847":{"exact":[],"prefix":["g6847.t1"]},"g9995":{"prefix":["g9995.t1"],"exact":[]},"g1809.t":{"prefix":["g1809.t1"],"exact":[]},"g8548.":{"prefix":["g8548.t1"],"exact":[]},"g4742.":{"prefix":["g4742.t1"],"exact":[]},"g1654.t":{"exact":[],"prefix":["g1654.t2","g1654.t1"]},"g9114.":{"prefix":["g9114.t1","g9114.t2"],"exact":[]},"g7284.":{"exact":[],"prefix":["g7284.t1"]},"g9526.t1":{"exact":[["g9526.t1",0,"g9526.t1","scaffold177size107572",71583,76380]],"prefix":[]},"g4107":{"exact":[],"prefix":["g4107.t1"]},"g9613":{"prefix":["g9613.t1"],"exact":[]},"g2256.t":{"exact":[],"prefix":["g2256.t1","g2256.t2","g2256.t3"]},"g3407.t":{"exact":[],"prefix":["g3407.t1"]},"g1960.t1":{"exact":[["g1960.t1",0,"g1960.t1","scaffold27size420939",398580,402594]],"prefix":[]},"scaffold172":{"prefix":["scaffold172size84450"],"exact":[]},"g8002":{"exact":[],"prefix":["g8002.t1"]},"scaffold483size3":{"prefix":["scaffold483size330"],"exact":[]},"g8210.t1":{"prefix":[],"exact":[["g8210.t1",0,"g8210.t1","scaffold136size209014",157265,159192]]},"g5240.":{"prefix":["g5240.t1"],"exact":[]},"g10349.":{"exact":[],"prefix":["g10349.t1"]},"g6195.t1":{"exact":[["g6195.t1",0,"g6195.t1","scaffold83size925501",788665,792360]],"prefix":[]},"g2507":{"prefix":["g2507.t1"],"exact":[]},"g10978.t1":{"exact":[["g10978.t1",0,"g10978.t1","scaffold310size5992",0,725]],"prefix":[]},"g6652.t1":{"prefix":[],"exact":[["g6652.t1",0,"g6652.t1","scaffold96size800595",528341,532836]]},"g6479.t":{"prefix":["g6479.t1"],"exact":[]},"g6713.t1":{"exact":[["g6713.t1",0,"g6713.t1","scaffold97size186622",34085,37510]],"prefix":[]},"g5400.":{"exact":[],"prefix":["g5400.t1"]},"g9838":{"exact":[],"prefix":["g9838.t1"]},"g2279.":{"exact":[],"prefix":["g2279.t1"]},"g4488.":{"prefix":["g4488.t1"],"exact":[]},"g5250.t1":{"exact":[["g5250.t1",0,"g5250.t1","scaffold67size576133",479185,482429]],"prefix":[]},"g1630.t":{"exact":[],"prefix":["g1630.t1"]},"g1821.t1":{"prefix":[],"exact":[["g1821.t1",0,"g1821.t1","scaffold25size587538",446976,450671]]},"g3249.t1":{"prefix":[],"exact":[["g3249.t1",0,"g3249.t1","scaffold42size402326",310721,315992]]},"g2073.t":{"exact":[],"prefix":["g2073.t1"]},"scaffold283":{"prefix":["scaffold283size11186"],"exact":[]},"g7069.t":{"prefix":["g7069.t1"],"exact":[]},"g8570":{"exact":[],"prefix":["g8570.t1"]},"g6802.t1":{"exact":[["g6802.t1",0,"g6802.t1","scaffold99size162308",148221,151820]],"prefix":[]},"g4956.":{"exact":[],"prefix":["g4956.t1"]},"g6786.":{"prefix":["g6786.t1"],"exact":[]},"g10669.t1":{"prefix":[],"exact":[["g10669.t1",0,"g10669.t1","scaffold245size52128",2125,9890]]},"g5597.t1":{"prefix":[],"exact":[["g5597.t1",0,"g5597.t1","scaffold74size87072",27676,30330]]},"g8338.t":{"prefix":["g8338.t1"],"exact":[]},"scaffold375size1603":{"exact":[["scaffold375size1603",null,"scaffold375size1603",null,0,1584,20000]],"prefix":[]},"g5890":{"prefix":["g5890.t1"],"exact":[]},"g7010.":{"exact":[],"prefix":["g7010.t1"]},"g893.t":{"prefix":["g893.t1"],"exact":[]},"g6352.":{"exact":[],"prefix":["g6352.t1"]},"g2273.t1":{"prefix":[],"exact":[["g2273.t1",0,"g2273.t1","scaffold33size816250",312477,316570]]},"g10509.":{"prefix":["g10509.t1"],"exact":[]},"scaffold5size201":{"prefix":["scaffold5size201749"],"exact":[]},"g10165.t1":{"exact":[["g10165.t1",0,"g10165.t1","scaffold204size48241",28595,31766]],"prefix":[]}}